facebook_crawl_api/__init__.py
facebook_crawl_api/__version__.py
facebook_crawl_api/core.py
facebook_crawl_api/function.py
facebook_crawl_api/model.py
facebook_crawl_api-1.1.0.dist-info/LICENSE
facebook_crawl_api-1.1.0.dist-info/METADATA
facebook_crawl_api-1.1.0.dist-info/WHEEL
facebook_crawl_api-1.1.0.dist-info/top_level.txt
facebook_crawl_api-1.1.0.dist-info/RECORD
