Metadata-Version: 2.1
Name: facebook-crawl-api
Version: 1.1.0
Summary: facebook数据采集器
Home-page: https://github.com/sheridan77/facebook_crawl_api.git
Author: Zrq
Author-email: zrq17777813307@163.com
License: Apache 2.0
Project-URL: Source, https://github.com/sheridan77/facebook_crawl_api.git
Requires-Python: >=3.7.0
License-File: LICENSE
Requires-Dist: requests (>=2.27.1)
Requires-Dist: lxml (>=4.7.1)
